torchdemon/__init__.py
torchdemon/inference_client.py
torchdemon/inference_model.py
torchdemon/inference_queue.py
torchdemon/inference_scheduler.py
torchdemon/inference_server.py
torchdemon/models.py
torchdemon/py.typed
torchdemon-0.0.3.dist-info/WHEEL
torchdemon-0.0.3.dist-info/METADATA
torchdemon-0.0.3.dist-info/RECORD
