Metadata-Version: 2.1
Name: torchdemon
Version: 0.0.3
Summary: Inference server for RL
Home-page: https://jacknurminen.github.io/torchdemon
License: MIT
Author: Jack Nurminen
Author-email: jack.nurminen@gmail.com
Requires-Python: >=3.8,<4.0
Classifier: Development Status :: 4 - Beta
Classifier: Intended Audience :: Developers
Classifier: License :: OSI Approved :: MIT License
Classifier: Operating System :: OS Independent
Classifier: Programming Language :: Python
Classifier: Programming Language :: Python :: 3
Classifier: Programming Language :: Python :: 3.10
Classifier: Programming Language :: Python :: 3.7
Classifier: Programming Language :: Python :: 3.8
Classifier: Programming Language :: Python :: 3.9
Classifier: Topic :: Software Development :: Libraries :: Python Modules
Classifier: Typing :: Typed
Requires-Dist: numpy (>=1.22.0,<2.0.0)
Requires-Dist: torch (>=1.10.1,<2.0.0)
Project-URL: Documentation, https://jacknurminen.github.io/torchdemon
Project-URL: Repository, https://github.com/jacknurminen/torchdemon
